acace_metrics_collector/__init__.py
acace_metrics_collector-0.1.0.dist-info/METADATA
acace_metrics_collector-0.1.0.dist-info/WHEEL
acace_metrics_collector-0.1.0.dist-info/RECORD
