Metadata-Version: 2.3
Name: acace_metrics_collector
Version: 0.1.0
Summary: Metrics collection utilities for ACACE
Author: ACACE Team
Author-email: team@acace.ai
Requires-Python: >=3.8,<4.0
Classifier: Programming Language :: Python :: 3
Classifier: Programming Language :: Python :: 3.8
Classifier: Programming Language :: Python :: 3.9
Classifier: Programming Language :: Python :: 3.10
Classifier: Programming Language :: Python :: 3.11
Classifier: Programming Language :: Python :: 3.12
Classifier: Programming Language :: Python :: 3.13
Requires-Dist: numpy (>=1.26.3,<2.0.0)
Requires-Dist: prometheus-client (>=0.19.0,<0.20.0)
